Workbook

Sheet Income Tracking
A1: INCOME TRACKING & MANAGEMENT | J1: Current Period: | K1: September 2025
A3: INCOME ENTRY | J3: INCOME SUMMARY
A5: Date | B5: Income Source | C5: Category | D5: Description | E5: Amount (KES) | F5: Payment Method | G5: Status | H5: Notes | J5: Total Received: | L5: =SUMIF(G6:G155,"Received",E6:E155)
J6: Pending Income: | L6: =SUMIF(G6:G155,"Pending",E6:E155)
J7: Expected Income: | L7: =SUMIF(G6:G155,"Expected",E6:E155)
J8: Regular Salary: | L8: =SUMIFS(E6:E155,B6:B155,"Regular Salary",G6:G155,"Received")
J9: Side Jobs/Freelance:
J10: Other Income: | L10: =SUMIF(G6:G155,"Received",E6:E155)-SUMIFS(E6:E155,B6:B155,"Regular Salary",G6:G155,"Received")
J11: Income Sources: | L11: =COUNTA(E6:E155)
J12: Average Income: | L12: =IFERROR(AVERAGE(E6:E155),0)
J14: INCOME BY SOURCE ANALYSIS
J16: Source | K16: Amount | L16: % of Total
J17: Regular Salary | K17: =SUMIF(B6:B155,J17,E6:E155) | L17: =IFERROR(K17/$L$5*100,0)
J18: Freelance Work | K18: =SUMIF(B6:B155,J18,E6:E155) | L18: =IFERROR(K18/$L$5*100,0)
J19: Side Job | K19: =SUMIF(B6:B155,J19,E6:E155) | L19: =IFERROR(K19/$L$5*100,0)
J20: Business Income | K20: =SUMIF(B6:B155,J20,E6:E155) | L20: =IFERROR(K20/$L$5*100,0)
J21: Investment Returns | K21: =SUMIF(B6:B155,J21,E6:E155) | L21: =IFERROR(K21/$L$5*100,0)
J22: Rental Income | K22: =SUMIF(B6:B155,J22,E6:E155) | L22: =IFERROR(K22/$L$5*100,0)
J23: Commission | K23: =SUMIF(B6:B155,J23,E6:E155) | L23: =IFERROR(K23/$L$5*100,0)
J24: Bonus | K24: =SUMIF(B6:B155,J24,E6:E155) | L24: =IFERROR(K24/$L$5*100,0)
J25: Gift | K25: =SUMIF(B6:B155,J25,E6:E155) | L25: =IFERROR(K25/$L$5*100,0)
J26: Tax Refund | K26: =SUMIF(B6:B155,J26,E6:E155) | L26: =IFERROR(K26/$L$5*100,0)

Sheet Expense Tracking
A1: EXPENSE TRACKING & MANAGEMENT | J1: Current Period: | K1: September 2025
A3: EXPENSE ENTRY | J3: EXPENSE SUMMARY | O3: EXPENSE CATEGORY GUIDE
A5: Date | B5: Category | C5: Subcategory | D5: Description | E5: Amount (KES) | F5: Payment Method | G5: Priority | H5: Notes | J5: Total Expenses: | L5: =SUM(E6:E205) | O5: Main Category | P5: Common Subcategories
J6: Essential: | L6: =SUMIF(G6:G205,"Essential",E6:E205) | O6: Rent & Utilities | P6: Rent, Electricity/KPLC, Water, Internet/WiFi, Gas/Cooking, Cable TV, Security, Garbage
J7: Important: | L7: =SUMIF(G6:G205,"Important",E6:E205) | O7: Food & Groceries | P7: Groceries, Restaurant, Fast Food, Coffee/Tea, Snacks, Fruits/Vegetables, Meat/Fish, Dairy
J8: Discretionary: | L8: =SUMIF(G6:G205,"Discretionary",E6:E205) | O8: Transport | P8: Fuel/Petrol, Uber/Taxi, Matatu/Bus, Car Service, Car Insurance, Parking, Toll Fees, Car Wash
J9: SACCO Savings: | L9: =SUMIF(B6:B205,"SACCO Savings",E6:E205) | O9: Healthcare | P9: Doctor Visit, Medicine, Hospital, Health Insurance, Dental, Eye Care, Medical Tests, Emergency
J10: Emergency Fund: | L10: =SUMIF(B6:B205,"Emergency Fund",E6:E205) | O10: Education | P10: School Fees, Books, Courses, Training, Stationery, Uniforms, Online Learning, Tutoring
J11: Transactions: | L11: =COUNTA(E6:E205) | O11: Entertainment | P11: Movies, Sports, Concerts, Subscriptions, Netflix/TV, Gaming, Hobbies, Outings
J12: Average Expense: | L12: =IFERROR(AVERAGE(E6:E205),0) | O12: Shopping | P12: Clothing, Shoes, Electronics, Household Items, Furniture, Appliances, Gifts, Online Shopping
O13: Personal Care | P13: Salon/Barber, Cosmetics, Toiletries, Gym, Spa, Grooming, Skincare, Wellness
O14: Insurance | P14: Life Insurance, Health Insurance, Car Insurance, Home Insurance, Travel Insurance, Device Insurance
O15: SACCO Savings | P15: Monthly Contribution, Extra Savings, Special Deposit, Share Capital
J16: EXPENSE BY CATEGORY | O16: Emergency Fund | P16: Emergency Savings, Contingency Fund, Reserve Fund, Rainy Day Fund
O17: Miscellaneous | P17: Airtime/Data, M-Pesa Charges, Bank Charges, Donations, Unexpected, Other
J18: Category | K18: Amount | L18: % of Total
J19: Regular Salary | K19: =SUMIF(B8:B157,J19,E8:E157) | L19: =IFERROR(K19/$L$5*100,0) | O19: IMPORTANT NOTES
J20: Freelance Work | K20: =SUMIF(B8:B157,J20,E8:E157) | L20: =IFERROR(K20/$L$5*100,0)
J21: Side Job | K21: =SUMIF(B8:B157,J21,E8:E157) | L21: =IFERROR(K21/$L$5*100,0) | O21: For Internet/WiFi: | P21: Select "Rent & Utilities" → Enter "Internet" in Subcategory
J22: Business Income | K22: =SUMIF(B8:B157,J22,E8:E157) | L22: =IFERROR(K22/$L$5*100,0) | O22: For Side Jobs: | P22: Track income in "Income Tracking" sheet
J23: Investment Returns | K23: =SUMIF(B8:B157,J23,E8:E157) | L23: =IFERROR(K23/$L$5*100,0) | O23: Priority Savings: | P23: SACCO & Emergency Fund should be paid first
J24: Rental Income | K24: =SUMIF(B8:B157,J24,E8:E157) | L24: =IFERROR(K24/$L$5*100,0) | O24: Subcategory Column: | P24: Type specific details in Column C for better tracking
J25: Commission | K25: =SUMIF(B8:B157,J25,E8:E157) | L25: =IFERROR(K25/$L$5*100,0)
J26: Bonus | K26: =SUMIF(B8:B157,J26,E8:E157) | L26: =IFERROR(K26/$L$5*100,0)
J27: Gift | K27: =SUMIF(B8:B157,J27,E8:E157) | L27: =IFERROR(K27/$L$5*100,0)
J28: Tax Refund | K28: =SUMIF(B8:B157,J28,E8:E157) | L28: =IFERROR(K28/$L$5*100,0)

Sheet Budget Setup
A1: MONTHLY BUDGET CONFIGURATION
A3: EXPECTED INCOME
A5: Income Source | B5: Monthly Amount | C5: Frequency | D5: Annual Total | E5: Notes
A6: Regular Salary | B6: 50000 | C6: Monthly | D6: =B6*12 | E6: Primary income
A7: Side Jobs/Freelance | B7: 0 | C7: Variable | D7: =B7*12 | E7: Additional income
A8: Other Income | B8: 0 | C8: Variable | D8: =B8*12 | E8: Miscellaneous
A11: EXPENSE BUDGET
A13: Expense Category | B13: Monthly Budget | C13: Priority | D13: Alert Threshold | E13: Notes
A14: Rent & Utilities | B14: 9000 | C14: Essential | D14: 100% | E14: Includes Internet
A15: Food & Groceries | B15: 9000 | C15: Essential | D15: 110% | E15: Monthly groceries
A16: Transport | B16: 9000 | C16: Essential | D16: 110% | E16: Fuel & maintenance
A17: SACCO Savings | B17: 10000 | C17: HIGH PRIORITY | D17: 90% | E17: Must meet target
A18: Emergency Fund | B18: 3000 | C18: HIGH PRIORITY | D18: 90% | E18: Must meet target
A19: Healthcare | B19: 2000 | C19: Important | D19: 120% | E19: Medical expenses
A20: Education | B20: 2000 | C20: Important | D20: 120% | E20: Courses & books
A21: Entertainment | B21: 2000 | C21: Discretionary | D21: 150% | E21: Leisure activities
A22: Shopping | B22: 1500 | C22: Discretionary | D22: 150% | E22: Clothing & items
A23: Personal Care | B23: 1000 | C23: Discretionary | D23: 150% | E23: Grooming & care
A24: Insurance | B24: 1500 | C24: Important | D24: 100% | E24: Life & health
A25: Miscellaneous | B25: 1000 | C25: Variable | D25: 200% | E25: Unexpected expenses
A26: TOTAL BUDGET | B26: =SUM(B14:B25)

Sheet Budget vs Actual
A1: BUDGET VS ACTUAL ANALYSIS
A3: INCOME ANALYSIS
A5: Income Source | B5: Budget | C5: Actual | D5: Variance | E5: Status
A6: Regular Salary | B6: ='Budget Setup'!B6 | C6: =SUMIFS('Income Tracking'!E:E,'Income Tracking'!B:B,"Regular Salary",'Income Tracking'!G:G,"Received") | D6: =C6-B6 | E6: =IF(C6>=B6,"Received","Pending")
A7: Side Jobs/Freelance | B7: ='Budget Setup'!B7 | C7: =SUMIFS('Income Tracking'!E:E,'Income Tracking'!B:B,"Side Job",'Income Tracking'!G:G,"Received")+SUMIFS('Income Tracking'!E:E,'Income Tracking'!B:B,"Freelance Work",'Income Tracking'!G:G,"Received") | D7: =C7-B7 | E7: =IF(C7>0,"Additional Income","None")
A8: Other Income | B8: ='Budget Setup'!B8 | C8: ='Income Tracking'!L5-C6-C7 | D8: =C8-B8 | E8: =IF(C8>0,"Extra Income","None")
A9: TOTAL INCOME | B9: =SUM(B6:B8) | C9: =SUM(C6:C8) | D9: =C9-B9 | E9: =IF(C9>=B9,"On Target","Below Target")
A11: EXPENSE ANALYSIS
A13: Category | B13: Budget | C13: Actual | D13: Remaining | E13: Usage % | F13: Status | G13: Priority | H13: Alert
A14: Rent & Utilities | B14: ='Budget Setup'!B14 | C14: =SUMIF('Expense Tracking'!B:B,"Rent & Utilities",'Expense Tracking'!E:E) | D14: =B14-C14 | E14: =IFERROR(C14/B14*100,0) | F14: =IF(E14>110,"Over Budget",IF(E14>90,"Warning","On Track")) | G14: Essential | H14: =IF(E14>120,"OVERSPENDING!","")
A15: Food & Groceries | B15: ='Budget Setup'!B15 | C15: =SUMIF('Expense Tracking'!B:B,"Food & Groceries",'Expense Tracking'!E:E) | D15: =B15-C15 | E15: =IFERROR(C15/B15*100,0) | F15: =IF(E15>110,"Over Budget",IF(E15>90,"Warning","On Track")) | G15: Essential | H15: =IF(E15>120,"OVERSPENDING!","")
A16: Transport | B16: ='Budget Setup'!B16 | C16: =SUMIF('Expense Tracking'!B:B,"Transport",'Expense Tracking'!E:E) | D16: =B16-C16 | E16: =IFERROR(C16/B16*100,0) | F16: =IF(E16>110,"Over Budget",IF(E16>90,"Warning","On Track")) | G16: Essential | H16: =IF(E16>120,"OVERSPENDING!","")
A17: SACCO Savings | B17: ='Budget Setup'!B17 | C17: =SUMIF('Expense Tracking'!B:B,"SACCO Savings",'Expense Tracking'!E:E) | D17: =B17-C17 | E17: =IFERROR(C17/B17*100,0) | F17: =IF(C17<B17,"BELOW TARGET","On Track") | G17: HIGH PRIORITY | H17: =IF(C17<B17*0.9,"URGENT: Target not met!","")
A18: Emergency Fund | B18: ='Budget Setup'!B18 | C18: =SUMIF('Expense Tracking'!B:B,"Emergency Fund",'Expense Tracking'!E:E) | D18: =B18-C18 | E18: =IFERROR(C18/B18*100,0) | F18: =IF(C18<B18,"BELOW TARGET","On Track") | G18: HIGH PRIORITY | H18: =IF(C18<B18*0.9,"URGENT: Target not met!","")
A19: Healthcare | B19: ='Budget Setup'!B19 | C19: =SUMIF('Expense Tracking'!B:B,"Healthcare",'Expense Tracking'!E:E) | D19: =B19-C19 | E19: =IFERROR(C19/B19*100,0) | F19: =IF(E19>110,"Over Budget",IF(E19>90,"Warning","On Track")) | G19: Important | H19: =IF(E19>120,"OVERSPENDING!","")
A20: Education | B20: ='Budget Setup'!B20 | C20: =SUMIF('Expense Tracking'!B:B,"Education",'Expense Tracking'!E:E) | D20: =B20-C20 | E20: =IFERROR(C20/B20*100,0) | F20: =IF(E20>110,"Over Budget",IF(E20>90,"Warning","On Track")) | G20: Important | H20: =IF(E20>120,"OVERSPENDING!","")
A21: Entertainment | B21: ='Budget Setup'!B21 | C21: =SUMIF('Expense Tracking'!B:B,"Entertainment",'Expense Tracking'!E:E) | D21: =B21-C21 | E21: =IFERROR(C21/B21*100,0) | F21: =IF(E21>110,"Over Budget",IF(E21>90,"Warning","On Track")) | G21: Discretionary | H21: =IF(E21>120,"OVERSPENDING!","")
A22: Shopping | B22: ='Budget Setup'!B22 | C22: =SUMIF('Expense Tracking'!B:B,"Shopping",'Expense Tracking'!E:E) | D22: =B22-C22 | E22: =IFERROR(C22/B22*100,0) | F22: =IF(E22>110,"Over Budget",IF(E22>90,"Warning","On Track")) | G22: Discretionary | H22: =IF(E22>120,"OVERSPENDING!","")
A23: Personal Care | B23: ='Budget Setup'!B23 | C23: =SUMIF('Expense Tracking'!B:B,"Personal Care",'Expense Tracking'!E:E) | D23: =B23-C23 | E23: =IFERROR(C23/B23*100,0) | F23: =IF(E23>110,"Over Budget",IF(E23>90,"Warning","On Track")) | G23: Discretionary | H23: =IF(E23>120,"OVERSPENDING!","")
A24: Insurance | B24: ='Budget Setup'!B24 | C24: =SUMIF('Expense Tracking'!B:B,"Insurance",'Expense Tracking'!E:E) | D24: =B24-C24 | E24: =IFERROR(C24/B24*100,0) | F24: =IF(E24>110,"Over Budget",IF(E24>90,"Warning","On Track")) | G24: Important | H24: =IF(E24>120,"OVERSPENDING!","")
A25: Miscellaneous | B25: ='Budget Setup'!B25 | C25: =SUMIF('Expense Tracking'!B:B,"Miscellaneous",'Expense Tracking'!E:E) | D25: =B25-C25 | E25: =IFERROR(C25/B25*100,0) | F25: =IF(E25>110,"Over Budget",IF(E25>90,"Warning","On Track")) | G25: Variable | H25: =IF(E25>120,"OVERSPENDING!","")
A26: TOTAL EXPENSES | B26: =SUM(B14:B25) | C26: =SUM(C14:C25) | D26: =B26-C26 | E26: =IFERROR(C26/B26*100,0) | F26: =IF(C26>B26,"Over Budget","Within Budget")
A28: NET BALANCE (Income - Expenses) | C28: =C9-C26

Sheet Dashboard
A1: FINANCIAL DASHBOARD & ANALYTICS
A3: KEY FINANCIAL METRICS | H3: CRITICAL ALERTS & WARNINGS
A5: Total Income | D5: Savings Rate | H5: SACCO Target: | I5: =IF('Budget vs Actual'!C17<'Budget vs Actual'!B17,"⚠ WARNING: Below target - KES "&TEXT('Budget vs Actual'!B17-'Budget vs Actual'!C17,"#,##0")&" short","✓ On track")
A6: ='Budget vs Actual'!C9 | D6: =IFERROR('Budget vs Actual'!C28/'Budget vs Actual'!C9*100,0) | H6: Emergency Fund: | I6: =IF('Budget vs Actual'!C18<'Budget vs Actual'!B18,"⚠ WARNING: Below target - KES "&TEXT('Budget vs Actual'!B18-'Budget vs Actual'!C18,"#,##0")&" short","✓ On track")
A7: All income sources | D7: % of income saved | H7: Budget Status: | I7: =IF('Budget vs Actual'!C26>'Budget vs Actual'!B26,"⚠ ALERT: Over budget by KES "&TEXT('Budget vs Actual'!C26-'Budget vs Actual'!B26,"#,##0"),"✓ Within budget")
H8: Overspending: | I8: =IF(COUNTIF('Budget vs Actual'!E14:E25,">110")>0,"⚠ Check "&COUNTIF('Budget vs Actual'!E14:E25,">110")&" categories over 110%","✓ All categories within limits")
A9: Total Expenses | D9: Budget Usage | H9: Net Position: | I9: =IF('Budget vs Actual'!C28<0,"⚠ DEFICIT: Expenses exceed income","✓ Positive cash flow")
A10: ='Budget vs Actual'!C26 | D10: ='Budget vs Actual'!E26
A11: All expenses | D11: % of budget used
A13: Net Savings | D13: SACCO Savings
A14: INCOME BREAKDOWN | H14: TOP EXPENSE CATEGORIES
A15: Income - Expenses | D15: Monthly contribution
A16: Source | B16: Budget | C16: Actual | D16: Status | H16: Category | I16: Budget | J16: Actual | K16: Usage % | L16: Status
A17: ='Budget vs Actual'!A6 | B17: ='Budget vs Actual'!B6 | C17: ='Budget vs Actual'!C6 | D17: ='Budget vs Actual'!E6 | H17: ='Budget vs Actual'!A14 | I17: ='Budget vs Actual'!B14 | J17: ='Budget vs Actual'!C14 | K17: ='Budget vs Actual'!E14 | L17: ='Budget vs Actual'!F14
A18: ='Budget vs Actual'!A7 | B18: ='Budget vs Actual'!B7 | C18: ='Budget vs Actual'!C7 | D18: ='Budget vs Actual'!E7 | H18: ='Budget vs Actual'!A15 | I18: ='Budget vs Actual'!B15 | J18: ='Budget vs Actual'!C15 | K18: ='Budget vs Actual'!E15 | L18: ='Budget vs Actual'!F15
A19: ='Budget vs Actual'!A8 | B19: ='Budget vs Actual'!B8 | C19: ='Budget vs Actual'!C8 | D19: ='Budget vs Actual'!E8 | H19: ='Budget vs Actual'!A16 | I19: ='Budget vs Actual'!B16 | J19: ='Budget vs Actual'!C16 | K19: ='Budget vs Actual'!E16 | L19: ='Budget vs Actual'!F16
H20: ='Budget vs Actual'!A17 | I20: ='Budget vs Actual'!B17 | J20: ='Budget vs Actual'!C17 | K20: ='Budget vs Actual'!E17 | L20: ='Budget vs Actual'!F17
H21: ='Budget vs Actual'!A18 | I21: ='Budget vs Actual'!B18 | J21: ='Budget vs Actual'!C18 | K21: ='Budget vs Actual'!E18 | L21: ='Budget vs Actual'!F18
H22: ='Budget vs Actual'!A19 | I22: ='Budget vs Actual'!B19 | J22: ='Budget vs Actual'!C19 | K22: ='Budget vs Actual'!E19 | L22: ='Budget vs Actual'!F19
A42: EXPENSE CATEGORY ANALYZER
A44: Select Category | B44: Amount Spent | C44: % of Total | D44: Budget | E44: Remaining | F44: Status
B45: =IF(A45="","",SUMIF('Expense Tracking'!B:B,A45,'Expense Tracking'!E:E)) | C45: =IF(A45="","",IFERROR(B45/'Budget vs Actual'!C26*100,0)) | D45: =IF(A45="","",IFERROR(VLOOKUP(A45,'Budget Setup'!A14:B25,2,FALSE),0)) | E45: =IF(A45="","",D45-B45) | F45: =IF(A45="","",IF(B45>D45,"Over Budget",IF(B45>D45*0.9,"Warning","On Track")))
B46: =IF(A46="","",SUMIF('Expense Tracking'!B:B,A46,'Expense Tracking'!E:E)) | C46: =IF(A46="","",IFERROR(B46/'Budget vs Actual'!C26*100,0)) | D46: =IF(A46="","",IFERROR(VLOOKUP(A46,'Budget Setup'!A14:B25,2,FALSE),0)) | E46: =IF(A46="","",D46-B46) | F46: =IF(A46="","",IF(B46>D46,"Over Budget",IF(B46>D46*0.9,"Warning","On Track")))
B47: =IF(A47="","",SUMIF('Expense Tracking'!B:B,A47,'Expense Tracking'!E:E)) | C47: =IF(A47="","",IFERROR(B47/'Budget vs Actual'!C26*100,0)) | D47: =IF(A47="","",IFERROR(VLOOKUP(A47,'Budget Setup'!A14:B25,2,FALSE),0)) | E47: =IF(A47="","",D47-B47) | F47: =IF(A47="","",IF(B47>D47,"Over Budget",IF(B47>D47*0.9,"Warning","On Track")))
B48: =IF(A48="","",SUMIF('Expense Tracking'!B:B,A48,'Expense Tracking'!E:E)) | C48: =IF(A48="","",IFERROR(B48/'Budget vs Actual'!C26*100,0)) | D48: =IF(A48="","",IFERROR(VLOOKUP(A48,'Budget Setup'!A14:B25,2,FALSE),0)) | E48: =IF(A48="","",D48-B48) | F48: =IF(A48="","",IF(B48>D48,"Over Budget",IF(B48>D48*0.9,"Warning","On Track")))
B49: =IF(A49="","",SUMIF('Expense Tracking'!B:B,A49,'Expense Tracking'!E:E)) | C49: =IF(A49="","",IFERROR(B49/'Budget vs Actual'!C26*100,0)) | D49: =IF(A49="","",IFERROR(VLOOKUP(A49,'Budget Setup'!A14:B25,2,FALSE),0)) | E49: =IF(A49="","",D49-B49) | F49: =IF(A49="","",IF(B49>D49,"Over Budget",IF(B49>D49*0.9,"Warning","On Track")))
B50: =IF(A50="","",SUMIF('Expense Tracking'!B:B,A50,'Expense Tracking'!E:E)) | C50: =IF(A50="","",IFERROR(B50/'Budget vs Actual'!C26*100,0)) | D50: =IF(A50="","",IFERROR(VLOOKUP(A50,'Budget Setup'!A14:B25,2,FALSE),0)) | E50: =IF(A50="","",D50-B50) | F50: =IF(A50="","",IF(B50>D50,"Over Budget",IF(B50>D50*0.9,"Warning","On Track")))
B51: =IF(A51="","",SUMIF('Expense Tracking'!B:B,A51,'Expense Tracking'!E:E)) | C51: =IF(A51="","",IFERROR(B51/'Budget vs Actual'!C26*100,0)) | D51: =IF(A51="","",IFERROR(VLOOKUP(A51,'Budget Setup'!A14:B25,2,FALSE),0)) | E51: =IF(A51="","",D51-B51) | F51: =IF(A51="","",IF(B51>D51,"Over Budget",IF(B51>D51*0.9,"Warning","On Track")))
B52: =IF(A52="","",SUMIF('Expense Tracking'!B:B,A52,'Expense Tracking'!E:E)) | C52: =IF(A52="","",IFERROR(B52/'Budget vs Actual'!C26*100,0)) | D52: =IF(A52="","",IFERROR(VLOOKUP(A52,'Budget Setup'!A14:B25,2,FALSE),0)) | E52: =IF(A52="","",D52-B52) | F52: =IF(A52="","",IF(B52>D52,"Over Budget",IF(B52>D52*0.9,"Warning","On Track")))
A54: Instructions: Select categories from dropdowns above to analyze specific expense categories

Sheet Monthly Trends
A1: MONTHLY TRENDS & ANALYSIS
A3: Category | B3: Jan | C3: Feb | D3: Mar | E3: Apr | F3: May | G3: Jun | H3: Jul | I3: Aug | J3: Sep | K3: Oct | L3: Nov | M3: Dec | N3: Total
A4: INCOME | B4: 0 | C4: 0 | D4: 0 | E4: 0 | F4: 0 | G4: 0 | H4: 0 | I4: 0 | J4: 0 | K4: 0 | L4: 0 | M4: 0 | N4: 0
A5: Rent & Utilities | B5: 0 | C5: 0 | D5: 0 | E5: 0 | F5: 0 | G5: 0 | H5: 0 | I5: 0 | J5: 0 | K5: 0 | L5: 0 | M5: 0 | N5: 0
A6: Food & Groceries | B6: 0 | C6: 0 | D6: 0 | E6: 0 | F6: 0 | G6: 0 | H6: 0 | I6: 0 | J6: 0 | K6: 0 | L6: 0 | M6: 0 | N6: 0
A7: Transport | B7: 0 | C7: 0 | D7: 0 | E7: 0 | F7: 0 | G7: 0 | H7: 0 | I7: 0 | J7: 0 | K7: 0 | L7: 0 | M7: 0 | N7: 0
A8: SACCO Savings | B8: 0 | C8: 0 | D8: 0 | E8: 0 | F8: 0 | G8: 0 | H8: 0 | I8: 0 | J8: 0 | K8: 0 | L8: 0 | M8: 0 | N8: 0
A9: Emergency Fund | B9: 0 | C9: 0 | D9: 0 | E9: 0 | F9: 0 | G9: 0 | H9: 0 | I9: 0 | J9: 0 | K9: 0 | L9: 0 | M9: 0 | N9: 0
A10: Healthcare | B10: 0 | C10: 0 | D10: 0 | E10: 0 | F10: 0 | G10: 0 | H10: 0 | I10: 0 | J10: 0 | K10: 0 | L10: 0 | M10: 0 | N10: 0
A11: Education | B11: 0 | C11: 0 | D11: 0 | E11: 0 | F11: 0 | G11: 0 | H11: 0 | I11: 0 | J11: 0 | K11: 0 | L11: 0 | M11: 0 | N11: 0
A12: Entertainment | B12: 0 | C12: 0 | D12: 0 | E12: 0 | F12: 0 | G12: 0 | H12: 0 | I12: 0 | J12: 0 | K12: 0 | L12: 0 | M12: 0 | N12: 0
A13: Shopping | B13: 0 | C13: 0 | D13: 0 | E13: 0 | F13: 0 | G13: 0 | H13: 0 | I13: 0 | J13: 0 | K13: 0 | L13: 0 | M13: 0 | N13: 0
A14: Personal Care | B14: 0 | C14: 0 | D14: 0 | E14: 0 | F14: 0 | G14: 0 | H14: 0 | I14: 0 | J14: 0 | K14: 0 | L14: 0 | M14: 0 | N14: 0
A15: Insurance | B15: 0 | C15: 0 | D15: 0 | E15: 0 | F15: 0 | G15: 0 | H15: 0 | I15: 0 | J15: 0 | K15: 0 | L15: 0 | M15: 0 | N15: 0
... A18: NET SAVINGS | B18: 0 | C18: 0 | D18: 0 | E18: 0 | F18: 0 | G18: 0 | H18: 0 | I18: 0 | J18: 0 | K18: 0 | L18: 0 | M18: 0 | N18: 0

Sheet Instructions
A1: COMPLETE USER GUIDE
A4: 📊 QUICK START GUIDE
A6: 1. RECORDING INCOME
A7: • Go to "Income Tracking" sheet
A8: • Select date when income received
A9: • Choose Income Source from dropdown (Salary, Side Job, Freelance, etc.)
A10: • Select Category (Monthly, One-time, Project-based)
A11: • Enter amount in KES
A12: • Mark Status as "Received" when payment confirmed
A13: • Income automatically adds to your available budget
A15: 2. RECORDING EXPENSES
A16: • Go to "Expense Tracking" sheet
... A75: • Use filters to analyze specific periods
